Metadata-Version: 2.1
Name: mkdocs-roamlinks-with-pdf-plugin
Version: 2.0.1
Summary: An MkDocs plugin
Home-page: https://github.com/jokulab/mkdocs-roamlinks-plugin
Author: jokulab
Author-email: 166611085+jokudev@users.noreply.github.com
License: MIT
Keywords: mkdocs
Classifier: Development Status :: 4 - Beta
Classifier: Intended Audience :: Developers
Classifier: Intended Audience :: Information Technology
Classifier: License :: OSI Approved :: MIT License
Classifier: Programming Language :: Python
Classifier: Programming Language :: Python :: 3.6
Classifier: Programming Language :: Python :: 3.7
Requires-Python: >=3.6
License-File: LICENSE
Requires-Dist: mkdocs>=1.0.4
Provides-Extra: dev
Requires-Dist: pytest; extra == "dev"
